.DS_Store
bqhus/__init__.py
bqhus/bqhus.py
bqhus/create_table.py
bqhus/export_table.py
bqhus/naming.py
bqhus/select.py
bqhus-0.1.2.dist-info/LICENSE
bqhus-0.1.2.dist-info/METADATA
bqhus-0.1.2.dist-info/WHEEL
bqhus-0.1.2.dist-info/top_level.txt
bqhus-0.1.2.dist-info/RECORD
