Metadata-Version: 2.1
Name: bqhus
Version: 0.1.2
Summary: bqhus: BigQuery helper utils.
Home-page: https://github.com/yokoe/bqhus
Download-URL: https://github.com/yokoe/bqhus
Author: yokoe
Author-email: kreuz45@kreuz45.com
Maintainer: yokoe
Maintainer-email: kreuz45@kreuz45.com
License: MIT
Keywords: bigquery
Classifier: License :: OSI Approved :: MIT License
Classifier: Programming Language :: Python :: 3.6
License-File: LICENSE
Requires-Dist: google-cloud-bigquery (>=3.4.0)
Requires-Dist: Jinja2 (>=3.0.0)
